sprite_hoai_thu/__init__.py
sprite_hoai_thu/spriteutil.py
sprite_hoai_thu-0.0.0.dist-info/LICENSE
sprite_hoai_thu-0.0.0.dist-info/METADATA
sprite_hoai_thu-0.0.0.dist-info/WHEEL
sprite_hoai_thu-0.0.0.dist-info/top_level.txt
sprite_hoai_thu-0.0.0.dist-info/RECORD
